LICENSE.txt
MANIFEST.in
README.rst
setup.py
xxxswf/__init__.py
xxxswf/xxxswf.py
xxxswf.egg-info/PKG-INFO
xxxswf.egg-info/SOURCES.txt
xxxswf.egg-info/dependency_links.txt
xxxswf.egg-info/entry_points.txt
xxxswf.egg-info/requires.txt
xxxswf.egg-info/top_level.txt